fracnetics/__init__.py
fracnetics/fracnetics.cpython-311-darwin.so
fracnetics-0.3.11.dist-info/METADATA
fracnetics-0.3.11.dist-info/WHEEL
fracnetics-0.3.11.dist-info/RECORD
