Metadata-Version: 2.4
Name: fracnetics
Version: 0.3.11
Summary: Genetic network programming with fractal expansion
Author-Email: =?utf-8?q?Fabian_K=C3=B6hnke?= <fabian.koehnke@googlemail.com>
License-Expression: MIT
Requires-Python: >=3.8
Requires-Dist: pybind11>=2.10.0
